{
    "class" : "Undertale",
    "daily_block" : 1612748010.826227,
    "damage" : 0,
    "deaths" : 0,
    "defence" : 0,
    "enemieskilled" : 1,
    "enemyhp" : 50,
    "equip" : "Stick",
    "exp" : 11,
    "gold" : 1103,
    "health" : 100,
    "hp_potions" : 3,
    "in_fight" : 0,
    "inv_armor" : [],
    "inventory" : [],
    "location" : "Ruins",
    "lootbag" : 0,
    "lvl" : 1,
    "max_health" : 100,
    "max_pot" : 12,
    "name" : "ItzJustJace79",
    "race" : "Normal",
    "resets" : 0,
    "rest_block" : 1612748064.8667648,
    "selected_enemy" : "None",
    "skills_learned" : [
        "Shoot"
    ],
    "wearing" : "Bandage"
}